{
  "type": "Program",
  "body": [
    {
      "type": "ImportDeclaration",
      "specifiers": [
        {
          "type": "ImportSpecifier",
          "local": {
            "type": "Identifier",
            "name": "iter",
            "range": [
              9,
              13
            ],
            "loc": {
              "start": {
                "line": 1,
                "column": 9
              },
              "end": {
                "line": 1,
                "column": 13
              }
            }
          },
          "imported": {
            "type": "Identifier",
            "name": "iter",
            "range": [
              9,
              13
            ],
            "loc": {
              "start": {
                "line": 1,
                "column": 9
              },
              "end": {
                "line": 1,
                "column": 13
              }
            }
          },
          "range": [
            9,
            13
          ],
          "loc": {
            "start": {
              "line": 1,
              "column": 9
            },
            "end": {
              "line": 1,
              "column": 13
            }
          }
        }
      ],
      "source": {
        "type": "Literal",
        "value": "..",
        "raw": "'..'",
        "range": [
          21,
          25
        ],
        "loc": {
          "start": {
            "line": 1,
            "column": 21
          },
          "end": {
            "line": 1,
            "column": 25
          }
        }
      },
      "range": [
        0,
        27
      ],
      "loc": {
        "start": {
          "line": 1,
          "column": 0
        },
        "end": {
          "line": 1,
          "column": 27
        }
      },
      "trailingComments": [
        {
          "type": "Block",
          "value": "*\n * Same as\n * <code>map( [ i , x ] => x , filter( [ i , x ] => (new Set( range( start ,\n * stop , step ) ) ).has( i ) , enumerate( iterable ) ) );</code>.\n *\n * @param {Iterable} iterable - The input iterable.\n * @param {Number} start - Where to start the slice.\n * @param {Number} stop - Where to stop the slice.\n * @param {Number} step - The step of the slice.\n * @returns {Iterator}\n ",
          "range": [
            29,
            422
          ],
          "loc": {
            "start": {
              "line": 3,
              "column": 0
            },
            "end": {
              "line": 13,
              "column": 3
            }
          }
        }
      ]
    },
    {
      "type": "ExportNamedDeclaration",
      "declaration": {
        "type": "FunctionDeclaration",
        "id": {
          "type": "Identifier",
          "name": "slice",
          "range": [
            440,
            445
          ],
          "loc": {
            "start": {
              "line": 14,
              "column": 17
            },
            "end": {
              "line": 14,
              "column": 22
            }
          }
        },
        "params": [
          {
            "type": "Identifier",
            "name": "iterable",
            "range": [
              448,
              456
            ],
            "loc": {
              "start": {
                "line": 14,
                "column": 25
              },
              "end": {
                "line": 14,
                "column": 33
              }
            }
          },
          {
            "type": "Identifier",
            "name": "start",
            "range": [
              459,
              464
            ],
            "loc": {
              "start": {
                "line": 14,
                "column": 36
              },
              "end": {
                "line": 14,
                "column": 41
              }
            }
          },
          {
            "type": "Identifier",
            "name": "stop",
            "range": [
              467,
              471
            ],
            "loc": {
              "start": {
                "line": 14,
                "column": 44
              },
              "end": {
                "line": 14,
                "column": 48
              }
            }
          },
          {
            "type": "Identifier",
            "name": "step",
            "range": [
              474,
              478
            ],
            "loc": {
              "start": {
                "line": 14,
                "column": 51
              },
              "end": {
                "line": 14,
                "column": 55
              }
            }
          }
        ],
        "body": {
          "type": "BlockStatement",
          "body": [
            {
              "type": "VariableDeclaration",
              "declarations": [
                {
                  "type": "VariableDeclarator",
                  "id": {
                    "type": "Identifier",
                    "name": "iterator",
                    "range": [
                      489,
                      497
                    ],
                    "loc": {
                      "start": {
                        "line": 16,
                        "column": 5
                      },
                      "end": {
                        "line": 16,
                        "column": 13
                      }
                    }
                  },
                  "init": {
                    "type": "CallExpression",
                    "callee": {
                      "type": "Identifier",
                      "name": "iter",
                      "range": [
                        500,
                        504
                      ],
                      "loc": {
                        "start": {
                          "line": 16,
                          "column": 16
                        },
                        "end": {
                          "line": 16,
                          "column": 20
                        }
                      }
                    },
                    "arguments": [
                      {
                        "type": "Identifier",
                        "name": "iterable",
                        "range": [
                          506,
                          514
                        ],
                        "loc": {
                          "start": {
                            "line": 16,
                            "column": 22
                          },
                          "end": {
                            "line": 16,
                            "column": 30
                          }
                        }
                      }
                    ],
                    "range": [
                      500,
                      516
                    ],
                    "loc": {
                      "start": {
                        "line": 16,
                        "column": 16
                      },
                      "end": {
                        "line": 16,
                        "column": 32
                      }
                    }
                  },
                  "range": [
                    489,
                    516
                  ],
                  "loc": {
                    "start": {
                      "line": 16,
                      "column": 5
                    },
                    "end": {
                      "line": 16,
                      "column": 32
                    }
                  }
                }
              ],
              "kind": "let",
              "range": [
                485,
                518
              ],
              "loc": {
                "start": {
                  "line": 16,
                  "column": 1
                },
                "end": {
                  "line": 16,
                  "column": 34
                }
              }
            },
            {
              "type": "WhileStatement",
              "test": {
                "type": "BinaryExpression",
                "operator": ">",
                "left": {
                  "type": "Identifier",
                  "name": "start",
                  "range": [
                    529,
                    534
                  ],
                  "loc": {
                    "start": {
                      "line": 18,
                      "column": 9
                    },
                    "end": {
                      "line": 18,
                      "column": 14
                    }
                  }
                },
                "right": {
                  "type": "Literal",
                  "value": 0,
                  "raw": "0",
                  "range": [
                    537,
                    538
                  ],
                  "loc": {
                    "start": {
                      "line": 18,
                      "column": 17
                    },
                    "end": {
                      "line": 18,
                      "column": 18
                    }
                  }
                },
                "range": [
                  529,
                  538
                ],
                "loc": {
                  "start": {
                    "line": 18,
                    "column": 9
                  },
                  "end": {
                    "line": 18,
                    "column": 18
                  }
                }
              },
              "body": {
                "type": "BlockStatement",
                "body": [
                  {
                    "type": "IfStatement",
                    "test": {
                      "type": "MemberExpression",
                      "computed": false,
                      "object": {
                        "type": "CallExpression",
                        "callee": {
                          "type": "MemberExpression",
                          "computed": false,
                          "object": {
                            "type": "Identifier",
                            "name": "iterator",
                            "range": [
                              551,
                              559
                            ],
                            "loc": {
                              "start": {
                                "line": 20,
                                "column": 7
                              },
                              "end": {
                                "line": 20,
                                "column": 15
                              }
                            }
                          },
                          "property": {
                            "type": "Identifier",
                            "name": "next",
                            "range": [
                              560,
                              564
                            ],
                            "loc": {
                              "start": {
                                "line": 20,
                                "column": 16
                              },
                              "end": {
                                "line": 20,
                                "column": 20
                              }
                            }
                          },
                          "range": [
                            551,
                            564
                          ],
                          "loc": {
                            "start": {
                              "line": 20,
                              "column": 7
                            },
                            "end": {
                              "line": 20,
                              "column": 20
                            }
                          }
                        },
                        "arguments": [],
                        "range": [
                          551,
                          566
                        ],
                        "loc": {
                          "start": {
                            "line": 20,
                            "column": 7
                          },
                          "end": {
                            "line": 20,
                            "column": 22
                          }
                        }
                      },
                      "property": {
                        "type": "Identifier",
                        "name": "done",
                        "range": [
                          567,
                          571
                        ],
                        "loc": {
                          "start": {
                            "line": 20,
                            "column": 23
                          },
                          "end": {
                            "line": 20,
                            "column": 27
                          }
                        }
                      },
                      "range": [
                        551,
                        571
                      ],
                      "loc": {
                        "start": {
                          "line": 20,
                          "column": 7
                        },
                        "end": {
                          "line": 20,
                          "column": 27
                        }
                      }
                    },
                    "consequent": {
                      "type": "ReturnStatement",
                      "argument": null,
                      "range": [
                        574,
                        582
                      ],
                      "loc": {
                        "start": {
                          "line": 20,
                          "column": 30
                        },
                        "end": {
                          "line": 20,
                          "column": 38
                        }
                      }
                    },
                    "alternate": null,
                    "range": [
                      546,
                      582
                    ],
                    "loc": {
                      "start": {
                        "line": 20,
                        "column": 2
                      },
                      "end": {
                        "line": 20,
                        "column": 38
                      }
                    }
                  },
                  {
                    "type": "ExpressionStatement",
                    "expression": {
                      "type": "UpdateExpression",
                      "operator": "--",
                      "argument": {
                        "type": "Identifier",
                        "name": "start",
                        "range": [
                          588,
                          593
                        ],
                        "loc": {
                          "start": {
                            "line": 22,
                            "column": 4
                          },
                          "end": {
                            "line": 22,
                            "column": 9
                          }
                        }
                      },
                      "prefix": true,
                      "range": [
                        586,
                        593
                      ],
                      "loc": {
                        "start": {
                          "line": 22,
                          "column": 2
                        },
                        "end": {
                          "line": 22,
                          "column": 9
                        }
                      }
                    },
                    "range": [
                      586,
                      595
                    ],
                    "loc": {
                      "start": {
                        "line": 22,
                        "column": 2
                      },
                      "end": {
                        "line": 22,
                        "column": 11
                      }
                    }
                  },
                  {
                    "type": "ExpressionStatement",
                    "expression": {
                      "type": "UpdateExpression",
                      "operator": "--",
                      "argument": {
                        "type": "Identifier",
                        "name": "stop",
                        "range": [
                          600,
                          604
                        ],
                        "loc": {
                          "start": {
                            "line": 23,
                            "column": 4
                          },
                          "end": {
                            "line": 23,
                            "column": 8
                          }
                        }
                      },
                      "prefix": true,
                      "range": [
                        598,
                        604
                      ],
                      "loc": {
                        "start": {
                          "line": 23,
                          "column": 2
                        },
                        "end": {
                          "line": 23,
                          "column": 8
                        }
                      }
                    },
                    "range": [
                      598,
                      606
                    ],
                    "loc": {
                      "start": {
                        "line": 23,
                        "column": 2
                      },
                      "end": {
                        "line": 23,
                        "column": 10
                      }
                    }
                  }
                ],
                "range": [
                  541,
                  610
                ],
                "loc": {
                  "start": {
                    "line": 18,
                    "column": 21
                  },
                  "end": {
                    "line": 25,
                    "column": 2
                  }
                }
              },
              "range": [
                521,
                610
              ],
              "loc": {
                "start": {
                  "line": 18,
                  "column": 1
                },
                "end": {
                  "line": 25,
                  "column": 2
                }
              }
            },
            {
              "type": "WhileStatement",
              "test": {
                "type": "BinaryExpression",
                "operator": ">",
                "left": {
                  "type": "Identifier",
                  "name": "stop",
                  "range": [
                    621,
                    625
                  ],
                  "loc": {
                    "start": {
                      "line": 27,
                      "column": 9
                    },
                    "end": {
                      "line": 27,
                      "column": 13
                    }
                  }
                },
                "right": {
                  "type": "Literal",
                  "value": 0,
                  "raw": "0",
                  "range": [
                    628,
                    629
                  ],
                  "loc": {
                    "start": {
                      "line": 27,
                      "column": 16
                    },
                    "end": {
                      "line": 27,
                      "column": 17
                    }
                  }
                },
                "range": [
                  621,
                  629
                ],
                "loc": {
                  "start": {
                    "line": 27,
                    "column": 9
                  },
                  "end": {
                    "line": 27,
                    "column": 17
                  }
                }
              },
              "body": {
                "type": "BlockStatement",
                "body": [
                  {
                    "type": "VariableDeclaration",
                    "declarations": [
                      {
                        "type": "VariableDeclarator",
                        "id": {
                          "type": "Identifier",
                          "name": "current",
                          "range": [
                            641,
                            648
                          ],
                          "loc": {
                            "start": {
                              "line": 29,
                              "column": 6
                            },
                            "end": {
                              "line": 29,
                              "column": 13
                            }
                          }
                        },
                        "init": {
                          "type": "CallExpression",
                          "callee": {
                            "type": "MemberExpression",
                            "computed": false,
                            "object": {
                              "type": "Identifier",
                              "name": "iterator",
                              "range": [
                                651,
                                659
                              ],
                              "loc": {
                                "start": {
                                  "line": 29,
                                  "column": 16
                                },
                                "end": {
                                  "line": 29,
                                  "column": 24
                                }
                              }
                            },
                            "property": {
                              "type": "Identifier",
                              "name": "next",
                              "range": [
                                660,
                                664
                              ],
                              "loc": {
                                "start": {
                                  "line": 29,
                                  "column": 25
                                },
                                "end": {
                                  "line": 29,
                                  "column": 29
                                }
                              }
                            },
                            "range": [
                              651,
                              664
                            ],
                            "loc": {
                              "start": {
                                "line": 29,
                                "column": 16
                              },
                              "end": {
                                "line": 29,
                                "column": 29
                              }
                            }
                          },
                          "arguments": [],
                          "range": [
                            651,
                            666
                          ],
                          "loc": {
                            "start": {
                              "line": 29,
                              "column": 16
                            },
                            "end": {
                              "line": 29,
                              "column": 31
                            }
                          }
                        },
                        "range": [
                          641,
                          666
                        ],
                        "loc": {
                          "start": {
                            "line": 29,
                            "column": 6
                          },
                          "end": {
                            "line": 29,
                            "column": 31
                          }
                        }
                      }
                    ],
                    "kind": "let",
                    "range": [
                      637,
                      668
                    ],
                    "loc": {
                      "start": {
                        "line": 29,
                        "column": 2
                      },
                      "end": {
                        "line": 29,
                        "column": 33
                      }
                    }
                  },
                  {
                    "type": "IfStatement",
                    "test": {
                      "type": "MemberExpression",
                      "computed": false,
                      "object": {
                        "type": "Identifier",
                        "name": "current",
                        "range": [
                          677,
                          684
                        ],
                        "loc": {
                          "start": {
                            "line": 31,
                            "column": 7
                          },
                          "end": {
                            "line": 31,
                            "column": 14
                          }
                        }
                      },
                      "property": {
                        "type": "Identifier",
                        "name": "done",
                        "range": [
                          685,
                          689
                        ],
                        "loc": {
                          "start": {
                            "line": 31,
                            "column": 15
                          },
                          "end": {
                            "line": 31,
                            "column": 19
                          }
                        }
                      },
                      "range": [
                        677,
                        689
                      ],
                      "loc": {
                        "start": {
                          "line": 31,
                          "column": 7
                        },
                        "end": {
                          "line": 31,
                          "column": 19
                        }
                      }
                    },
                    "consequent": {
                      "type": "ReturnStatement",
                      "argument": null,
                      "range": [
                        692,
                        700
                      ],
                      "loc": {
                        "start": {
                          "line": 31,
                          "column": 22
                        },
                        "end": {
                          "line": 31,
                          "column": 30
                        }
                      }
                    },
                    "alternate": null,
                    "range": [
                      672,
                      700
                    ],
                    "loc": {
                      "start": {
                        "line": 31,
                        "column": 2
                      },
                      "end": {
                        "line": 31,
                        "column": 30
                      }
                    }
                  },
                  {
                    "type": "ExpressionStatement",
                    "expression": {
                      "type": "YieldExpression",
                      "argument": {
                        "type": "MemberExpression",
                        "computed": false,
                        "object": {
                          "type": "Identifier",
                          "name": "current",
                          "range": [
                            710,
                            717
                          ],
                          "loc": {
                            "start": {
                              "line": 33,
                              "column": 8
                            },
                            "end": {
                              "line": 33,
                              "column": 15
                            }
                          }
                        },
                        "property": {
                          "type": "Identifier",
                          "name": "value",
                          "range": [
                            718,
                            723
                          ],
                          "loc": {
                            "start": {
                              "line": 33,
                              "column": 16
                            },
                            "end": {
                              "line": 33,
                              "column": 21
                            }
                          }
                        },
                        "range": [
                          710,
                          723
                        ],
                        "loc": {
                          "start": {
                            "line": 33,
                            "column": 8
                          },
                          "end": {
                            "line": 33,
                            "column": 21
                          }
                        }
                      },
                      "delegate": false,
                      "range": [
                        704,
                        723
                      ],
                      "loc": {
                        "start": {
                          "line": 33,
                          "column": 2
                        },
                        "end": {
                          "line": 33,
                          "column": 21
                        }
                      }
                    },
                    "range": [
                      704,
                      725
                    ],
                    "loc": {
                      "start": {
                        "line": 33,
                        "column": 2
                      },
                      "end": {
                        "line": 33,
                        "column": 23
                      }
                    }
                  },
                  {
                    "type": "ExpressionStatement",
                    "expression": {
                      "type": "UpdateExpression",
                      "operator": "--",
                      "argument": {
                        "type": "Identifier",
                        "name": "stop",
                        "range": [
                          731,
                          735
                        ],
                        "loc": {
                          "start": {
                            "line": 35,
                            "column": 4
                          },
                          "end": {
                            "line": 35,
                            "column": 8
                          }
                        }
                      },
                      "prefix": true,
                      "range": [
                        729,
                        735
                      ],
                      "loc": {
                        "start": {
                          "line": 35,
                          "column": 2
                        },
                        "end": {
                          "line": 35,
                          "column": 8
                        }
                      }
                    },
                    "range": [
                      729,
                      737
                    ],
                    "loc": {
                      "start": {
                        "line": 35,
                        "column": 2
                      },
                      "end": {
                        "line": 35,
                        "column": 10
                      }
                    }
                  },
                  {
                    "type": "VariableDeclaration",
                    "declarations": [
                      {
                        "type": "VariableDeclarator",
                        "id": {
                          "type": "Identifier",
                          "name": "n",
                          "range": [
                            745,
                            746
                          ],
                          "loc": {
                            "start": {
                              "line": 37,
                              "column": 6
                            },
                            "end": {
                              "line": 37,
                              "column": 7
                            }
                          }
                        },
                        "init": {
                          "type": "Identifier",
                          "name": "step",
                          "range": [
                            749,
                            753
                          ],
                          "loc": {
                            "start": {
                              "line": 37,
                              "column": 10
                            },
                            "end": {
                              "line": 37,
                              "column": 14
                            }
                          }
                        },
                        "range": [
                          745,
                          753
                        ],
                        "loc": {
                          "start": {
                            "line": 37,
                            "column": 6
                          },
                          "end": {
                            "line": 37,
                            "column": 14
                          }
                        }
                      }
                    ],
                    "kind": "let",
                    "range": [
                      741,
                      755
                    ],
                    "loc": {
                      "start": {
                        "line": 37,
                        "column": 2
                      },
                      "end": {
                        "line": 37,
                        "column": 16
                      }
                    }
                  },
                  {
                    "type": "WhileStatement",
                    "test": {
                      "type": "BinaryExpression",
                      "operator": ">",
                      "left": {
                        "type": "Identifier",
                        "name": "n",
                        "range": [
                          767,
                          768
                        ],
                        "loc": {
                          "start": {
                            "line": 39,
                            "column": 10
                          },
                          "end": {
                            "line": 39,
                            "column": 11
                          }
                        }
                      },
                      "right": {
                        "type": "Literal",
                        "value": 1,
                        "raw": "1",
                        "range": [
                          771,
                          772
                        ],
                        "loc": {
                          "start": {
                            "line": 39,
                            "column": 14
                          },
                          "end": {
                            "line": 39,
                            "column": 15
                          }
                        }
                      },
                      "range": [
                        767,
                        772
                      ],
                      "loc": {
                        "start": {
                          "line": 39,
                          "column": 10
                        },
                        "end": {
                          "line": 39,
                          "column": 15
                        }
                      }
                    },
                    "body": {
                      "type": "BlockStatement",
                      "body": [
                        {
                          "type": "IfStatement",
                          "test": {
                            "type": "MemberExpression",
                            "computed": false,
                            "object": {
                              "type": "CallExpression",
                              "callee": {
                                "type": "MemberExpression",
                                "computed": false,
                                "object": {
                                  "type": "Identifier",
                                  "name": "iterator",
                                  "range": [
                                    786,
                                    794
                                  ],
                                  "loc": {
                                    "start": {
                                      "line": 41,
                                      "column": 8
                                    },
                                    "end": {
                                      "line": 41,
                                      "column": 16
                                    }
                                  }
                                },
                                "property": {
                                  "type": "Identifier",
                                  "name": "next",
                                  "range": [
                                    795,
                                    799
                                  ],
                                  "loc": {
                                    "start": {
                                      "line": 41,
                                      "column": 17
                                    },
                                    "end": {
                                      "line": 41,
                                      "column": 21
                                    }
                                  }
                                },
                                "range": [
                                  786,
                                  799
                                ],
                                "loc": {
                                  "start": {
                                    "line": 41,
                                    "column": 8
                                  },
                                  "end": {
                                    "line": 41,
                                    "column": 21
                                  }
                                }
                              },
                              "arguments": [],
                              "range": [
                                786,
                                801
                              ],
                              "loc": {
                                "start": {
                                  "line": 41,
                                  "column": 8
                                },
                                "end": {
                                  "line": 41,
                                  "column": 23
                                }
                              }
                            },
                            "property": {
                              "type": "Identifier",
                              "name": "done",
                              "range": [
                                802,
                                806
                              ],
                              "loc": {
                                "start": {
                                  "line": 41,
                                  "column": 24
                                },
                                "end": {
                                  "line": 41,
                                  "column": 28
                                }
                              }
                            },
                            "range": [
                              786,
                              806
                            ],
                            "loc": {
                              "start": {
                                "line": 41,
                                "column": 8
                              },
                              "end": {
                                "line": 41,
                                "column": 28
                              }
                            }
                          },
                          "consequent": {
                            "type": "ReturnStatement",
                            "argument": null,
                            "range": [
                              809,
                              817
                            ],
                            "loc": {
                              "start": {
                                "line": 41,
                                "column": 31
                              },
                              "end": {
                                "line": 41,
                                "column": 39
                              }
                            }
                          },
                          "alternate": null,
                          "range": [
                            781,
                            817
                          ],
                          "loc": {
                            "start": {
                              "line": 41,
                              "column": 3
                            },
                            "end": {
                              "line": 41,
                              "column": 39
                            }
                          }
                        },
                        {
                          "type": "ExpressionStatement",
                          "expression": {
                            "type": "UpdateExpression",
                            "operator": "--",
                            "argument": {
                              "type": "Identifier",
                              "name": "n",
                              "range": [
                                824,
                                825
                              ],
                              "loc": {
                                "start": {
                                  "line": 43,
                                  "column": 5
                                },
                                "end": {
                                  "line": 43,
                                  "column": 6
                                }
                              }
                            },
                            "prefix": true,
                            "range": [
                              822,
                              825
                            ],
                            "loc": {
                              "start": {
                                "line": 43,
                                "column": 3
                              },
                              "end": {
                                "line": 43,
                                "column": 6
                              }
                            }
                          },
                          "range": [
                            822,
                            827
                          ],
                          "loc": {
                            "start": {
                              "line": 43,
                              "column": 3
                            },
                            "end": {
                              "line": 43,
                              "column": 8
                            }
                          }
                        }
                      ],
                      "range": [
                        775,
                        832
                      ],
                      "loc": {
                        "start": {
                          "line": 39,
                          "column": 18
                        },
                        "end": {
                          "line": 45,
                          "column": 3
                        }
                      }
                    },
                    "range": [
                      759,
                      832
                    ],
                    "loc": {
                      "start": {
                        "line": 39,
                        "column": 2
                      },
                      "end": {
                        "line": 45,
                        "column": 3
                      }
                    }
                  }
                ],
                "range": [
                  632,
                  836
                ],
                "loc": {
                  "start": {
                    "line": 27,
                    "column": 20
                  },
                  "end": {
                    "line": 47,
                    "column": 2
                  }
                }
              },
              "range": [
                613,
                836
              ],
              "loc": {
                "start": {
                  "line": 27,
                  "column": 1
                },
                "end": {
                  "line": 47,
                  "column": 2
                }
              }
            }
          ],
          "range": [
            481,
            839
          ],
          "loc": {
            "start": {
              "line": 14,
              "column": 58
            },
            "end": {
              "line": 49,
              "column": 1
            }
          }
        },
        "generator": true,
        "expression": false,
        "range": [
          430,
          839
        ],
        "loc": {
          "start": {
            "line": 14,
            "column": 7
          },
          "end": {
            "line": 49,
            "column": 1
          }
        },
        "leadingComments": [
          {
            "type": "Block",
            "value": "*\n * Same as\n * <code>map( [ i , x ] => x , filter( [ i , x ] => (new Set( range( start ,\n * stop , step ) ) ).has( i ) , enumerate( iterable ) ) );</code>.\n *\n * @param {Iterable} iterable - The input iterable.\n * @param {Number} start - Where to start the slice.\n * @param {Number} stop - Where to stop the slice.\n * @param {Number} step - The step of the slice.\n * @returns {Iterator}\n ",
            "range": [
              29,
              422
            ],
            "loc": {
              "start": {
                "line": 3,
                "column": 0
              },
              "end": {
                "line": 13,
                "column": 3
              }
            }
          }
        ],
        "trailingComments": []
      },
      "specifiers": [],
      "source": null,
      "range": [
        423,
        839
      ],
      "loc": {
        "start": {
          "line": 14,
          "column": 0
        },
        "end": {
          "line": 49,
          "column": 1
        }
      },
      "leadingComments": [
        {
          "type": "Block",
          "value": "*\n * Same as\n * <code>map( [ i , x ] => x , filter( [ i , x ] => (new Set( range( start ,\n * stop , step ) ) ).has( i ) , enumerate( iterable ) ) );</code>.\n *\n * @param {Iterable} iterable - The input iterable.\n * @param {Number} start - Where to start the slice.\n * @param {Number} stop - Where to stop the slice.\n * @param {Number} step - The step of the slice.\n * @returns {Iterator}\n ",
          "range": [
            29,
            422
          ],
          "loc": {
            "start": {
              "line": 3,
              "column": 0
            },
            "end": {
              "line": 13,
              "column": 3
            }
          }
        }
      ]
    }
  ],
  "sourceType": "module",
  "range": [
    0,
    839
  ],
  "loc": {
    "start": {
      "line": 1,
      "column": 0
    },
    "end": {
      "line": 49,
      "column": 1
    }
  },
  "comments": [
    {
      "type": "Block",
      "value": "*\n * Same as\n * <code>map( [ i , x ] => x , filter( [ i , x ] => (new Set( range( start ,\n * stop , step ) ) ).has( i ) , enumerate( iterable ) ) );</code>.\n *\n * @param {Iterable} iterable - The input iterable.\n * @param {Number} start - Where to start the slice.\n * @param {Number} stop - Where to stop the slice.\n * @param {Number} step - The step of the slice.\n * @returns {Iterator}\n ",
      "range": [
        29,
        422
      ],
      "loc": {
        "start": {
          "line": 3,
          "column": 0
        },
        "end": {
          "line": 13,
          "column": 3
        }
      }
    }
  ]
}